sensorizer/__init__.py
sensorizer/data_classes.py
sensorizer/queue_interface.py
sensorizer/sensor_emulator.py
sensorizer/version.py
sensorizer-0.0.3.dist-info/LICENSE
sensorizer-0.0.3.dist-info/METADATA
sensorizer-0.0.3.dist-info/WHEEL
sensorizer-0.0.3.dist-info/top_level.txt
sensorizer-0.0.3.dist-info/RECORD
