Metadata-Version: 2.1
Name: sensorizer
Version: 0.0.3
Summary: Timeseries data generation and preparation for batch jobs at scale
Home-page: https://github.com/equinor/sensorizer
Author: Jesus Gazol
Author-email: jgaz@equinor.com
Maintainer: jgaz@equinor.com
Maintainer-email: jgaz@equinor.com
License: GPL 3
Project-URL: Source, https://github.com/
Project-URL: Tracker, https://github.com/
Keywords: IoT,sensor
Platform: any
Classifier: Development Status :: 3 - Alpha
Classifier: Intended Audience :: Developers
Classifier: License :: OSI Approved :: GNU General Public License v3 (GPLv3)
Classifier: Operating System :: POSIX
Classifier: Operating System :: Microsoft :: Windows
Classifier: Operating System :: MacOS :: MacOS X
Classifier: Topic :: Software Development :: Libraries
Classifier: Programming Language :: Python :: 3.7
Classifier: Programming Language :: Python :: 3.8
Requires-Python: >=3.7
Requires-Dist: numpy (>=1.16.3)
Requires-Dist: fastavro (>=0.22.13)
Requires-Dist: azure-eventhub (==1.3.1)
Provides-Extra: dev
Requires-Dist: pre-commit (>=2.1.1) ; extra == 'dev'
Provides-Extra: docs
Requires-Dist: sphinx (<3,>=2.0.0) ; extra == 'docs'
Requires-Dist: towncrier (>=18.5.0) ; extra == 'docs'
Requires-Dist: pygments-github-lexers (>=0.0.5) ; extra == 'docs'
Requires-Dist: sphinxcontrib-autoprogram (>=0.1.5) ; extra == 'docs'
Provides-Extra: testing
Requires-Dist: pytest (==5.3.5) ; extra == 'testing'
Requires-Dist: pytest-cov ; extra == 'testing'
